README.md
setup.py
Development_tools.egg-info/PKG-INFO
Development_tools.egg-info/SOURCES.txt
Development_tools.egg-info/dependency_links.txt
Development_tools.egg-info/entry_points.txt
Development_tools.egg-info/namespace_packages.txt
Development_tools.egg-info/top_level.txt
orangecontrib/__init__.py
orangecontrib/development_tools/__init__.py
orangecontrib/development_tools/widgets/MetManagement.py
orangecontrib/development_tools/widgets/VarManagement.py
orangecontrib/development_tools/widgets/WrapMessageBox.py
orangecontrib/development_tools/widgets/__init__.py
orangecontrib/development_tools/widgets/goto.py
orangecontrib/development_tools/widgets/orange_sub_workflow.py
orangecontrib/development_tools/widgets/shared_functions.py
orangecontrib/development_tools/widgets/shared_variables.py
orangecontrib/development_tools/widgets/subworkflow_input.py
orangecontrib/development_tools/widgets/subworkflow_output.py
orangecontrib/development_tools/widgets/icons/Chatbot.svg
orangecontrib/development_tools/widgets/icons/DocumentEater.svg
orangecontrib/development_tools/widgets/icons/Embeddings.svg
orangecontrib/development_tools/widgets/icons/LanguageModel.svg
orangecontrib/development_tools/widgets/icons/Logo_HKH.svg
orangecontrib/development_tools/widgets/icons/TextPreprocessing.svg
orangecontrib/development_tools/widgets/icons/file-transfer.png
orangecontrib/development_tools/widgets/icons/goto.png
orangecontrib/development_tools/widgets/icons/input.png
orangecontrib/development_tools/widgets/icons/jcm_open_file_resize_alpha_channel.png
orangecontrib/development_tools/widgets/icons/output.png
orangecontrib/development_tools/widgets/icons/subworkflow_output.png
orangecontrib/development_tools/widgets/icons/tool.png
orangecontrib/development_tools/widgets/kernel_function/Table_management.py
orangecontrib/development_tools/widgets/kernel_function/Utils_box.py
orangecontrib/development_tools/widgets/kernel_function/supp_moi_bis.tab
orangecontrib/development_tools/widgets/kernel_function/supp_moi_bis_permutation_tototo.tab
orangecontrib/development_tools/widgets/kernel_function/zoubida.dada
orangecontrib/development_tools/widgets/kernel_function/zoubida2.dada
orangecontrib/development_tools/widgets/widget_designer/goto.ui
